itop_cli/__init__.py
itop_cli/__main__.py
itop_cli/action.py
itop_cli/cli.py
itop_cli/connection.py
itop_cli/create.py
itop_cli/export_data.py
itop_cli/extension.py
itop_cli/find.py
itop_cli/import_data.py
itop_cli/safe_delete.py
itop_cli/search_keys.py
itop_cli/threaded_deletion.py
itop_cli/update.py
itop_cli-2.0.0.dist-info/METADATA
itop_cli-2.0.0.dist-info/WHEEL
itop_cli-2.0.0.dist-info/entry_points.txt
itop_cli-2.0.0.dist-info/RECORD
