Metadata-Version: 2.1
Name: itop-cli
Version: 2.0.0
Summary: 
License: PSF
Author: dnum-dip
Author-email: dnum-dip@unistra.fr
Requires-Python: >=3.9,<4.0
Classifier: License :: Other/Proprietary License
Classifier: Programming Language :: Python :: 3
Classifier: Programming Language :: Python :: 3.9
Classifier: Programming Language :: Python :: 3.10
Classifier: Programming Language :: Python :: 3.11
Classifier: Programming Language :: Python :: 3.12
Classifier: Programming Language :: Python :: 3.13
Requires-Dist: docopt (>=0.6.2,<0.7.0)
Requires-Dist: itopy (>=0.1.7,<0.2.0)
